fac/__init__.py
fac/api.py
fac/db.py
fac/files.py
fac/main.py
fac/mods.py
fac/save.py
fac/save_diff.py
fac/utils.py
fac/commands/__init__.py
fac/commands/all.py
fac/commands/enable.py
fac/commands/fetch.py
fac/commands/hold.py
fac/commands/install.py
fac/commands/list.py
fac/commands/make_compatible.py
fac/commands/pack.py
fac/commands/remove.py
fac/commands/search.py
fac/commands/show.py
fac/commands/update.py
fac_cli-0.9.data/data/share/zsh/site-functions/_fac
fac_cli-0.9.dist-info/DESCRIPTION.rst
fac_cli-0.9.dist-info/METADATA
fac_cli-0.9.dist-info/RECORD
fac_cli-0.9.dist-info/WHEEL
fac_cli-0.9.dist-info/entry_points.txt
fac_cli-0.9.dist-info/metadata.json
fac_cli-0.9.dist-info/top_level.txt
