Metadata-Version: 2.0
Name: fac-cli
Version: 0.9
Summary: Command-line mod manager for Factorio (install, update...).
Home-page: https://github.com/mickael9/fac
Author: Mickaël Thomas
Author-email: mickael9@gmail.com
License: MIT
Keywords: factorio mod manager updater installer
Platform: UNKNOWN
Classifier: Development Status :: 3 - Alpha
Classifier: Environment :: Console
Classifier: Operating System :: OS Independent
Classifier: License :: OSI Approved :: MIT License
Classifier: Programming Language :: Python :: 3 :: Only
Classifier: Programming Language :: Python :: 3.5
Classifier: Topic :: Games/Entertainment
Requires-Dist: requests
Requires-Dist: appdirs
Requires-Dist: packaging
